{"The Kingdom":{"The Kingdom":{"internalLink":{"count":2,"lastUpdated":1688813794568}}},"elven-absinthe-drug":{"elven-absinthe-drug":{"internalLink":{"count":1,"lastUpdated":1687153745364}}},"initiative":{"initiative":{"currentFile":{"count":1,"lastUpdated":1687308873546}}},"Chadidoc Thundercock":{"Chadidoc Thundercock":{"internalLink":{"count":2,"lastUpdated":1687688008768}}},"npc-military-foot-soldier":{"npc-military-foot-soldier":{"internalLink":{"count":2,"lastUpdated":1687679087918}}},"longspear":{"longspear":{"currentFile":{"count":1,"lastUpdated":1687679467700}}},"Garridan":{"Garridan":{"currentFile":{"count":1,"lastUpdated":1687688052419}}},"presence":{"presence":{"currentFile":{"count":1,"lastUpdated":1688812365718}}},"expedition":{"expedition":{"currentFile":{"count":2,"lastUpdated":1688813518999}}},"cerberus-worm":{"cerberus-worm":{"internalLink":{"count":1,"lastUpdated":1688813091298}}},"recall":{"recall":{"currentFile":{"count":1,"lastUpdated":1688813143270}}},"responsible":{"responsible":{"currentFile":{"count":3,"lastUpdated":1688815192080}}},"outside":{"outside":{"currentFile":{"count":1,"lastUpdated":1688813384650}}},"warmonger":{"warmonger":{"internalLink":{"count":1,"lastUpdated":1688813398717}}},"troll-warden":{"troll-warden":{"internalLink":{"count":1,"lastUpdated":1688813615898}}},"Ydersius":{"Ydersius":{"internalLink":{"count":1,"lastUpdated":1688813721649}}},"remorhaz":{"remorhaz":{"internalLink":{"count":1,"lastUpdated":1688814090274}}},"insurgent":{"insurgent":{"currentFile":{"count":1,"lastUpdated":1688815298149}}},"convenient":{"convenient":{"currentFile":{"count":1,"lastUpdated":1688815595444}}},"information":{"information":{"currentFile":{"count":1,"lastUpdated":1688815698145}}},"expedition.It":{"expedition.It":{"currentFile":{"count":1,"lastUpdated":1688816109077}}},"Questions":{"Questions":{"currentFile":{"count":1,"lastUpdated":1688816548685}}},"demidavious":{"demidavious":{"currentFile":{"count":1,"lastUpdated":1688816616756}}},"Smuggler's Shiv":{"Smuggler's Shiv":{"internalLink":{"count":1,"lastUpdated":1688818083556}}},"Winfred":{"Winfred":{"currentFile":{"count":1,"lastUpdated":1688818917055}}}}